calculatepi_pkg/__init__.py
calculatepi_pkg/calcpi.py
calculatepi_pkg_Ramen_Nood1ez-0.0.11.dist-info/METADATA
calculatepi_pkg_Ramen_Nood1ez-0.0.11.dist-info/WHEEL
calculatepi_pkg_Ramen_Nood1ez-0.0.11.dist-info/license
calculatepi_pkg_Ramen_Nood1ez-0.0.11.dist-info/top_level.txt
calculatepi_pkg_Ramen_Nood1ez-0.0.11.dist-info/RECORD
