Metadata-Version: 2.1
Name: calculatepi-pkg-Ramen-Nood1ez
Version: 0.0.11
Summary: A program that calculates pi
Home-page: https://github.com/Ramen-Nood1ez/CalculatePi/
Author: Ramen Nood1ez
Author-email: 
License: UNKNOWN
Project-URL: Bug Tracker, https://github.com/Ramen-Nood1ez/CalculatePi/issues
Platform: UNKNOWN
Classifier: Programming Language :: Python :: 3
Classifier: Operating System :: OS Independent
Requires-Python: >=3.6
